consulock/__init__.py
consulock-0.4.3.dist-info/METADATA
consulock-0.4.3.dist-info/WHEEL
consulock-0.4.3.dist-info/top_level.txt
consulock-0.4.3.dist-info/RECORD
