Metadata-Version: 2.1
Name: consulock
Version: 0.4.3
Summary: a distributed lock based on consul
Home-page: https://github.com/haarcuba/consulock
Author: Yoav Kleinberger
Author-email: haarcuba@gmail.com
License: UNKNOWN
Keywords: consul
Platform: UNKNOWN
Classifier: Programming Language :: Python
Requires-Dist: python-consul2
Provides-Extra: testing
Requires-Dist: pytest ; extra == 'testing'
Requires-Dist: testix ; extra == 'testing'
